clientAPI/__init__.py
clientAPI/base.py
clientAPI/client.py
clientAPI/mixin.py
clientAPI/setup.py
clientAPI/utils.py
CSG_test-0.1.2.dist-info/METADATA
CSG_test-0.1.2.dist-info/WHEEL
CSG_test-0.1.2.dist-info/top_level.txt
CSG_test-0.1.2.dist-info/RECORD
