Metadata-Version: 2.1
Name: CSG-test
Version: 0.1.2
Summary: Test CSG library
Home-page: https://csgenome.org/
Author: Ani Ramadoss
Author-email: aniramadoss2002@vt.edu
License: MIT
Platform: UNKNOWN
Classifier: Intended Audience :: Developers
Classifier: License :: OSI Approved :: MIT License
Classifier: Programming Language :: Python
Classifier: Programming Language :: Python :: 3
Classifier: Programming Language :: Python :: 3.6
Classifier: Programming Language :: Python :: 3.7
Classifier: Programming Language :: Python :: 3.8
Classifier: Programming Language :: Python :: 3.9
Classifier: Operating System :: OS Independent
Requires-Dist: flask
Requires-Dist: requests
